voxels-0.0.1a0.data/purelib/dearpygui/__init__.py
voxels-0.0.1a0.data/purelib/dearpygui/dearpygui.py
voxels-0.0.1a0.data/purelib/dearpygui/demo.py
voxels-0.0.1a0.data/purelib/dearpygui/logger.py
voxels-0.0.1a0.data/purelib/dearpygui/themes.py
voxels-0.0.1a0.dist-info/LICENSE
voxels-0.0.1a0.dist-info/METADATA
voxels-0.0.1a0.dist-info/WHEEL
voxels-0.0.1a0.dist-info/top_level.txt
voxels-0.0.1a0.dist-info/RECORD
