Metadata-Version: 2.1
Name: voxels
Version: 0.0.1a0
Summary: DearPyGui: A simple Python GUI Toolkit
Home-page: https://github.com/hoffstadt/DearPyGui
Author: Jonathan Hoffstadt and Preston Cothren
Author-email: jonathanhoffstadt@yahoo.com
License: MIT
